{"author": null, "casenumber": "Adm in Per 790/1998", "casename": "Precious Wishes Limited v Sinoble Metalloy International (Pte) Ltd", "citation": "[2000] SGHC 5", "coram": "Judith Prakash J", "counsel": "Augustine Liew with Keuk Ping Yang (Haridass Ho & Partners) for the plaintiffs; Tan Siah Yong (Piah Tan & Partners) for the defendants", "headings": [{"type": "h_b", "text": "Background", "para": 1}, {"type": "h", "text": "The evidence", "para": 11}], "decorations": [{"italic": [[113, 126]]}, {}, {}, {}, {}, {}, {}, {}, {}, {}, {}, {}, {}, {}, {}, {}, {}, {}, {"nobr": [[521, 1048]], "quote": [[286, 1047]]}, {}, {}, {}, {}, {}, {"quote": [[349, 756]]}, {"quote": [[442, 702]]}, {}, {}, {}, {}, {}, {}, {}, {}]}