{"author": "V K Rajah J:", "casenumber": "Suit 834/2004, SIC 5807/2004", "casename": "Asian Corporate Services (SEA) Pte Ltd v Impact Pacific Consultants Pte Ltd and Others", "citation": "[2005] SGHC 138", "coram": "V K Rajah J", "counsel": "Koh Kok Wah, Andy Leck and Dinesh Dhillion (Wong and Leow LLC) for the plaintiff; Salem Ibrahim and Shankar Kumar (Salem Ibrahim and Partners) for the first, second, and fourth to seventh defendants; Jimmy Yim SC and Kelvin Tan (Drew and Napier LLC) for the third defendant", "decorations": [{"italic": [[14, 36], [708, 753]], "quote-1": [[99, 349]], "nobr": [[754, 766]]}, {}, {"italic": [[385, 393]]}, {}, {}, {"italic": [[683, 693]]}, {}, {"italic": [[87, 96]]}, {"italic": [[55, 63]]}, {}, {}, {}, {}, {}, {}, {}, {"italic": [[30, 41]]}, {"italic": [[391, 401], [884, 893]]}, {"italic": [[220, 322], [546, 551], [607, 652], [785, 796], [1176, 1188]], "quote-1": [[220, 529], [604, 745], [1202, 1483]], "quote-2": [[746, 803], [804, 884], [885, 1201]]}, {"italic": [[242, 260], [290, 293], [301, 315], [471, 492], [612, 685], [1088, 1114]], "quote-1": [[190, 433], [434, 435], [436, 686], [687, 703]]}, {"italic": [[149, 157], [316, 352], [451, 473]], "quote-1": [[220, 409], [410, 540], [541, 557]]}, {"italic": [[182, 325], [587, 670], [725, 1049], [1187, 1292]], "quote-1": [[182, 586], [587, 1293], [1294, 1310]]}, {"italic": [[1221, 1232]]}, {"italic": [[176, 221], [227, 232]]}, {"italic": [[174, 235]], "nobr": [[236, 253]]}, {"italic": [[92, 98], [202, 262]], "nobr": [[263, 279]]}, {"italic": [[566, 569]]}, {"italic": [[115, 147], [255, 270], [501, 513], [521, 864], [956, 1002]], "nobr": [[148, 165], [1003, 1017]], "quote-1": [[239, 882]]}, {"italic": [[744, 750], [1417, 1427]]}, {"italic": [[766, 812], [819, 824], [840, 843]]}, {"italic": [[120, 145], [192, 218], [254, 276], [307, 475], [889, 901], [911, 955], [1068, 1071], [1086, 1108], [1321, 1364]], "nobr": [[146, 163], [1365, 1381]], "quote-1": [[178, 475], [476, 477], [478, 1133], [1134, 1150]]}, {"italic": [[204, 210], [954, 995], [1144, 1147], [1267, 1277]]}, {"italic": [[139, 184]], "nobr": [[185, 200]]}, {}, {}, {}, {"italic": [[648, 655], [685, 692]]}, {"italic": [[153, 198], [243, 354], [366, 461], [546, 580], [591, 657]], "quote-1": [[206, 674]]}], "tags": ["Civil Procedure/Anton piller orders"], "tags-parsed": ["Civil Procedure/Anton piller orders/Application to set aside order granted on allegation of conspiracy to injure applicant's business/Whether prima facie case of conspiracy established/Whether very serious damage sustained in absence of grant of order/Whether real risk of destruction of evidence existing/Whether effect of order excessive or disproportionate to its legitimate goal/Whether applicant making proper enquiries before making application for order"]}