{"author": "Judith Prakash J:", "casenumber": "Suit 892/2004", "casename": "Abdul Jalil bin Ahmad bin Talib and Others v A Formation Construction Pte Ltd", "citation": "[2006] SGHC 171", "coram": "Judith Prakash J", "counsel": "Aloysius Leng (Abrahamlow LLC) for the plaintiffs; Anthony Netto and Michael Yap (Teo Keng Siang & Partners) for the defendant", "decorations": [{}, {}, {}, {}, {}, {}, {}, {}, {}, {}, {}, {"quote-1": [[709, 818], [1642, 1792], [2092, 2196]], "quote-2": [[819, 1028], [1029, 1210], [1611, 1641], [1793, 1988], [1989, 2091]], "quote-3": [[1211, 1329], [1330, 1438], [1439, 1542], [1543, 1610]]}, {}, {"quote-1": [[511, 904]]}, {"italic": [[693, 696]]}, {"judgm-2": [[199, 472], [473, 684], [685, 849], [850, 932]], "judgm-3": [[933, 1104], [1105, 1273], [1274, 1520]]}, {"italic": [[111, 121]]}, {}, {}, {}, {}, {"judgm-2": [[657, 788], [789, 954], [955, 1031]]}, {}, {}, {}, {"italic": [[602, 608]]}, {}, {"italic": [[172, 174]]}, {}, {"italic": [[297, 327], [344, 349], [574, 606]], "nobr": [[328, 341]]}, {"italic": [[39, 44], [549, 554], [729, 736], [922, 932], [2065, 2070], [2072, 2083], [2108, 2122], [2519, 2529], [2610, 2647]], "quote-1": [[633, 1081], [1082, 1083], [1084, 1759], [1760, 1761], [1762, 2442], [2443, 2444], [2445, 3054], [3055, 3077]]}, {}, {}, {}, {"quote-1": [[1452, 1700]]}, {}, {}, {}, {"italic": [[226, 245]]}, {}, {"judgm-2": [[655, 919], [920, 1533], [1534, 2045]]}, {"italic": [[963, 982]]}, {"italic": [[260, 292], [318, 374]], "nobr": [[375, 389]]}, {"italic": [[370, 389], [396, 401], [749, 768], [881, 892]]}, {}, {}], "tags": ["Equity/Estoppel", "Contract/Consideration/Forbearance", "Contract/Formation/Capacity of parties"], "tags-parsed": ["Contract/Consideration/Forbearance/Defendant giving up any right to make claim against trustees for damages for breach of terms in lease agreement by accepting compromise offered/Whether such forbearance amounting to consideration for compromise agreement", "Contract/Formation/Capacity of parties/Will constituting trust stipulating trust to be managed by two trustees at all times/Sole trustee having power to carry on all necessary business of trust only until new trustees appointed/Business of trust to manage immoveable properties/Whether sole trustee having power to authorise compromise agreement regarding rental arrears of such immovable properties/Whether sole trustee's solicitors having ostensible authority to effect compromise agreement", "Equity/Estoppel/Defendant giving up any right to make claim against trustees for damages for breach of terms in lease agreement by accepting compromise offered/Defendant discharging obligations under compromise agreement/Whether inequitable for plaintiffs to refuse to honour compromise agreement on ground that such agreement not lawfully entered into"]}