{"author": "Belinda Ang Saw Ean J:", "casenumber": "OS 1088/2007", "casename": "Fustar Chemicals Ltd v Ong Soo Hwa (liquidator of Fustar Chemicals Pte Ltd)", "citation": "[2008] SGHC 198", "coram": "Belinda Ang Saw Ean J", "counsel": "N Sreenivasan (Straits Law Practice LLC) for the plaintiffs; Kannan Ramesh (Tan Kok Quan Partnership) for the defendant", "decorations": [{}, {}, {}, {"italic": [[102, 112]]}, {"judgm-2": [[366, 474], [475, 557], [558, 660], [661, 792], [793, 884]]}, {}, {}, {}, {}, {}, {"italic": [[205, 208]]}, {}, {}, {}, {"italic": [[556, 561], [993, 996]]}, {}, {}, {"italic": [[75, 78], [315, 389], [407, 418]], "nobr": [[390, 404]]}, {"italic": [[113, 164], [181, 210], [212, 263], [280, 343], [461, 485], [525, 535]], "nobr": [[165, 181], [264, 280], [344, 360]]}, {}, {}, {}, {"italic": [[196, 247], [334, 345], [377, 419], [441, 497]], "nobr": [[248, 263], [420, 436], [498, 514]]}, {"italic": [[227, 251], [511, 514]]}, {}, {"italic": [[1518, 1552]], "nobr": [[1553, 1568]]}, {"italic": [[221, 228], [234, 333], [388, 395], [508, 571], [935, 989], [1165, 1247]], "nobr": [[334, 350], [572, 590], [990, 1005], [1248, 1264]]}, {"judgm-2": [[335, 585], [586, 893], [894, 1138], [1139, 1289]]}, {"judgm-2": [[47, 155], [156, 232], [233, 517], [518, 674], [675, 743], [744, 866]]}, {}, {}, {"italic": [[287, 315]], "quote-1": [[338, 1001]]}, {"italic": [[600, 620], [655, 692], [1043, 1063], [1164, 1191]], "nobr": [[621, 637], [1064, 1080]], "quote-1": [[1245, 1744]]}, {"italic": [[0, 28]], "quote-1": [[388, 892], [893, 894], [895, 1300]]}, {"italic": [[554, 593]]}, {"italic": [[0, 16], [23, 28]], "quote-1": [[810, 1242], [1243, 1710]]}, {}, {"italic": [[113, 132]]}, {"italic": [[388, 421]]}, {}, {}, {"italic": [[421, 450], [452, 457]]}, {}], "tags": ["Companies/Winding up"], "tags-parsed": ["Companies/Winding up/Proof of debt/Debt owed by associated company/Effect of lack of primary documents/Whether liquidator entitled to go behind audited accounts and account confirmations to require satisfactory evidence of the debt proved for/Whether liquidator bound by estoppels against the company or an account stated with the company"]}