{"author": "Judith Prakash J:", "casenumber": "Suit 427/2006, RA 306/2007, 319/2007, 320/2007, 321/2007, 322/2007, 323/2007, 324/2007", "casename": "Ser Kim Koi and Another v Fulton William Merrell and Others", "citation": "[2008] SGHC 23", "coram": "Judith Prakash J", "counsel": "Philip Jeyaretnam SC, Ajinderpal Singh and Jay Lee (Rodyk & Davidson LLP) for the plaintiffs; Khoo Boo Jin and Tan Hsuan Boon (Wee Swee Teow & Co) for the first defendant; Chua Sui Tong and Janice Goh (WongPartnership LLP) for the second to fourth defendants; Moiz Sithawalla and Yeo Boon Tat (Tan Rajah & Cheah) for the fifth defendant", "decorations": [{}, {}, {}, {"judgm-2": [[130, 157], [158, 191], [192, 259], [260, 703]]}, {}, {}, {"italic": [[305, 364], [388, 401], [435, 494], [519, 528]]}, {"italic": [[454, 464]], "quote-1": [[515, 1026]]}, {"italic": [[201, 211], [649, 662], [697, 743], [767, 775], [1054, 1063], [1068, 1081], [1125, 1135]]}, {}, {"italic": [[218, 231], [1909, 1917], [2396, 2414], [2419, 2432], [2703, 2712]], "quote-1": [[1112, 1185], [1186, 1561], [1562, 1960], [1961, 2761]]}, {"italic": [[0, 13], [330, 340], [345, 353], [433, 441], [890, 892]]}, {}, {}, {"italic": [[370, 376], [420, 448], [668, 768], [2032, 2037]], "quote-1": [[248, 419], [805, 1222], [1223, 2140]], "quote-2": [[420, 667], [668, 804]]}, {"italic": [[273, 292]], "quote-1": [[319, 615], [616, 1779], [1780, 2200]], "bold": [[1097, 1294]]}, {"italic": [[633, 643]]}, {}, {"italic": [[928, 935]]}, {}, {}, {}, {"italic": [[385, 395]]}, {}, {}, {}, {}, {}, {}, {}], "tags": ["Civil Procedure/Discovery of documents"], "tags-parsed": ["Civil Procedure/Discovery of documents/Whether parties allowed to amend list of documents filed for discovery purposes to delete items/Whether documents protected by litigation privilege/Order 20 r 8(1) Rules of Court (Cap 322, R 5, 2006 Rev Ed)"]}