{"author": "Woo Bih Li J:", "casenumber": "Suit 875/2008, RA 24/2009", "casename": "BNP Paribas Wealth Management v Lam Chi Kin David", "citation": "[2009] SGHC 117", "coram": "Woo Bih Li J", "counsel": "K Muralidharan Pillai (Rajah &Tann LLP) for the plaintiff/respondent; Soh Gim Chuan (Soh Wong & Yap) for the defendant/appellant", "decorations": [{}, {}, {}, {}, {}, {"judgm-2": [[373, 487], [488, 599], [600, 685]]}, {"judgm-2": [[174, 251], [252, 326]]}, {}, {}, {"italic": [[97, 99]]}, {}, {}, {}, {}, {}, {}, {}, {}, {}], "tags": ["Credit and Security"]}