{"author": "Lee Seiu Kin J:", "casenumber": "Suit 773/2008, RA 7/2009", "casename": "Merrill Lynch Pierce, Fenner & Smith Inc v Prem Ramchand Harjani and Another", "citation": "[2009] SGHC 133", "coram": "Lee Seiu Kin J", "counsel": "Hri Kumar Nair SC and James Low (Drew & Napier LLC) for the plaintiff; Denis Tan (Toh Tan LLP) for the first defendant; Anthony Lee Hwee Khiam, Pua Lee Siang and Shermaine Lim (Bih Li & Lee) for the second defendant", "decorations": [{}, {}, {"quote-1": [[419, 616], [617, 765], [766, 876], [877, 977]]}, {}, {"italic": [[644, 654]]}, {}, {"judgm-2": [[575, 805], [806, 1362], [1363, 1476], [1477, 1774], [1775, 1918], [1919, 2235], [2236, 2291]], "italic": [[1345, 1347], [1757, 1759], [2214, 2216]]}, {}, {}, {}, {}, {}, {}, {"judgm-2": [[344, 514], [515, 639]]}, {"bold": [[254, 539], [541, 969], [971, 1312]], "italic": [[523, 530], [533, 539]], "quote-1": [[254, 540], [541, 970], [971, 1313], [1314, 1336]]}, {"quote-1": [[47, 154], [155, 156], [157, 525], [526, 1083]]}, {"italic": [[211, 268], [621, 638]], "bold": [[352, 399]], "quote-1": [[352, 399], [400, 616], [617, 638], [639, 1041], [1042, 1292], [1293, 1315], [1410, 1910], [1911, 2257]]}, {"italic": [[357, 437], [457, 463], [489, 495], [796, 802]], "nobr": [[438, 454]]}, {"italic": [[479, 485]]}, {"italic": [[216, 263], [283, 290], [393, 400]], "nobr": [[264, 280]], "quote-1": [[433, 631]]}, {"italic": [[142, 185], [334, 372]], "nobr": [[373, 390]], "quote-1": [[513, 790]]}, {"italic": [[3, 9]]}, {"italic": [[3, 10]]}, {"judgm-2": [[939, 1109], [1110, 1862], [1863, 2008], [4710, 5117], [5118, 5289], [9706, 9957]], "judgm-3": [[2009, 2091], [2355, 2504], [2946, 3096], [3481, 3952], [3953, 4019], [4325, 4472], [5290, 5359], [5550, 5942], [5943, 6888], [6889, 7301], [7302, 7536], [7537, 7741], [7742, 8721], [8722, 8813], [8814, 9093], [9366, 9705]], "quote-3": [[2092, 2354], [2505, 2945], [3097, 3480], [4020, 4324], [4473, 4709], [5360, 5441], [5442, 5501], [5502, 5549], [9094, 9365], [9958, 10547]], "italic": [[5115, 5116], [8747, 8749], [9980, 10159], [10276, 10529]]}, {}, {}, {}, {}, {}, {"italic": [[902, 937]], "nobr": [[938, 954]]}, {}], "tags": ["Arbitration/Stay of court proceedings"], "tags-parsed": ["Arbitration/Stay of court proceedings/Mandatory stay under International Arbitration Act (Cap 143A, 2002 Rev Ed)/Express terms prohibited set-off from liability/Whether customer entitled to set off against its liability", "Arbitration/Stay of court proceedings/Mandatory stay under International Arbitration Act (Cap 143A, 2002 Rev Ed)/Whether arbitration agreement applicable/Whether mere refusal to pay amount indisputably due constituted dispute/Section 6 International Arbitration Act (Cap 143A, 2002 Rev Ed)"]}