{"author": "Lee Yeow Wee David AR:", "casenumber": "Suit No 326 of 2004 (Summons No 5313 of 2009)", "casename": "Beckkett Pte Ltd v Deutsche Bank AG", "citation": "[2010] SGHC 55", "coram": "Lee Yeow Wee David AR", "counsel": "Mr Davinder Singh SC, Ms Cheryl Tan and Mr Pardeep Singh (Drew & Napier LLC) for the plaintiff; Mr Ang Cheng Hock SC, Mr William Ong, Mr Loong Tse Chuan and Mr Kenneth Lim (Allen & Gledhill LLP) for the defendant.", "decorations": [{}, {}, {}, {}, {"italic": [[549, 591], [647, 689]]}, {"quote-1": [[372, 596], [597, 710], [711, 1014], [1015, 1318], [1319, 1531], [1532, 1856], [1857, 2015], [2016, 2109], [2110, 2325]]}, {"quote-1": [[92, 473], [474, 762], [763, 1020], [1021, 1288], [1289, 1358]]}, {"italic": [[409, 426], [645, 655], [724, 734], [1392, 1400]], "quote-1": [[379, 806], [807, 1048], [1049, 1401]]}, {}, {}, {}, {}, {}, {}, {}, {}, {}, {}, {}, {}, {}, {"quote-1": [[228, 434]]}, {"italic": [[706, 761]]}, {"italic": [[183, 240], [257, 274]]}, {}, {"italic": [[491, 503]]}, {}, {}, {}, {}, {"italic": [[247, 295], [315, 336], [608, 618], [1133, 1209]]}, {"italic": [[650, 655], [1272, 1289], [1327, 1364]], "bold": [[1382, 1447]], "quote-1": [[1073, 1466]]}, {"italic": [[293, 303], [329, 337]]}, {}, {}, {"italic": [[566, 578], [651, 683], [695, 933]], "bold": [[651, 933]], "quote-1": [[489, 952]]}, {"italic": [[166, 220], [238, 257], [378, 397]]}, {}, {"italic": [[709, 718], [739, 773], [792, 805]]}, {}, {"italic": [[46, 60]]}, {"italic": [[108, 127]]}, {}, {}, {"italic": [[159, 169]]}, {"italic": [[501, 516], [541, 575]]}, {}, {"italic": [[61, 78], [83, 155]]}, {"italic": [[68, 84]], "bold": [[589, 651]], "quote-1": [[124, 745]]}, {"italic": [[757, 818], [866, 879]], "quote-1": [[1049, 2313]]}, {"italic": [[36, 47], [142, 153], [1576, 1591]], "bold": [[2057, 2153]], "quote-1": [[819, 2452]]}, {}, {"italic": [[89, 155], [174, 183]], "bold": [[682, 764]], "quote-1": [[378, 783]]}, {"italic": [[107, 147], [162, 178], [245, 254]], "bold": [[687, 830]], "quote-1": [[256, 848]]}, {}, {}, {}, {}, {}, {}, {}, {}, {"italic": [[45, 94], [131, 145]], "bold": [[374, 404]], "quote-1": [[365, 1012], [1013, 1190]]}, {"italic": [[69, 83], [391, 411], [441, 448], [515, 522], [548, 565], [745, 771], [789, 826], [2293, 2309]], "quote-1": [[185, 2825]]}, {}, {"italic": [[86, 105], [906, 923]]}, {"italic": [[31, 45], [132, 195], [215, 242], [1044, 1122], [1361, 1378], [1413, 1475]], "quote-1": [[126, 421], [827, 1503]], "quote-2": [[422, 505], [506, 578], [579, 683], [684, 826]]}, {"italic": [[453, 467]], "bold": [[1546, 1652], [1654, 1751]], "quote-1": [[486, 1876]]}, {}, {"italic": [[108, 176], [199, 204], [1436, 1469]], "bold": [[1123, 1425], [1519, 1836], [1912, 2014], [2064, 2176], [2448, 2649]], "quote-1": [[863, 1429], [1430, 1841], [1842, 2289], [2290, 2668]]}, {}, {"italic": [[246, 308], [327, 336]], "bold": [[828, 1155]], "quote-1": [[416, 1160], [1161, 1582]]}, {}, {"italic": [[49, 58]]}, {}, {}, {}, {}, {}, {}, {}, {"italic": [[52, 73], [1098, 1119], [1147, 1168]]}, {"italic": [[126, 202], [221, 231], [299, 383], [405, 455], [525, 534]], "quote-1": [[606, 1259]]}, {"italic": [[32, 42], [174, 183]]}, {}, {}, {}, {"italic": [[99, 118]]}, {}, {}, {}, {"italic": [[122, 131], [136, 149], [284, 293], [453, 462], [620, 635], [733, 742], [911, 928], [1026, 1035], [1201, 1216], [1263, 1272], [1337, 1352], [1593, 1602], [1783, 1801]]}, {"italic": [[39, 52], [135, 144], [199, 212], [257, 266]]}, {}, {}, {}, {"italic": [[220, 233], [290, 316]]}, {}, {"italic": [[268, 330]]}, {"italic": [[337, 358], [990, 1011]]}, {}, {"italic": [[270, 281]]}, {}, {}, {}, {}, {"italic": [[49, 54]]}, {"italic": [[273, 278]]}, {}, {}, {}, {}, {}, {}, {"italic": [[212, 221], [226, 276]]}, {}, {}, {"italic": [[671, 770], [1323, 1396]]}, {}, {}, {}, {}, {}, {}, {}, {}], "tags": ["Civil Procedure", "Conflict of Laws"]}