{"author": "Belinda Ang Saw Ean J:", "casenumber": "Admiralty in Rem No 113 of 2008", "casename": "The \u201cDolphina\u201d", "citation": "[2011] SGHC 273", "coram": "Belinda Ang Saw Ean J", "counsel": "Vivian Ang, Kenny Yap and Bryna Yeo (Allen & Gledhill LLP) for the plaintiff; Prem Gurbani and Bernard Yee (Gurbani & Co) for the defendant.", "decorations": [{}, {"judgm-2": [[591, 1083], [1084, 1587], [1588, 1801], [1802, 1921]]}, {}, {}, {}, {"italic": [[133, 141]]}, {"italic": [[208, 216]]}, {}, {"judgm-2": [[96, 455], [456, 684], [685, 1007], [1008, 1892], [1893, 2074]], "italic": [[1001, 1004], [1668, 1676]]}, {"italic": [[125, 135]], "judgm-2": [[278, 331], [332, 455], [456, 638], [639, 792]]}, {"judgm-2": [[178, 289], [290, 412], [413, 464], [465, 626]]}, {}, {}, {}, {}, {}, {}, {}, {}, {"italic": [[292, 294]]}, {"italic": [[50, 53], [776, 786]], "judgm-2": [[400, 475], [476, 703], [704, 911]]}, {"italic": [[624, 627]]}, {}, {"italic": [[191, 199]]}, {}, {}, {"italic": [[62, 70]]}, {"underline": [[298, 299]], "italic": [[545, 548]], "quote-1": [[275, 875]]}, {}, {}, {"italic": [[142, 150]]}, {"italic": [[37, 45], [288, 298]]}, {"italic": [[107, 117], [353, 363]], "quote-1": [[377, 563], [564, 804], [805, 806], [807, 1107], [1108, 1358], [1359, 1360]]}, {"italic": [[157, 163]]}, {"italic": [[27, 35], [226, 236]]}, {"italic": [[425, 433]]}, {}, {}, {}, {"italic": [[139, 141]]}, {"italic": [[249, 265], [270, 289], [369, 386], [391, 411]]}, {"italic": [[207, 209]]}, {"quote-1": [[224, 332], [333, 622]]}, {"italic": [[216, 251]], "quote-1": [[157, 284]]}, {"quote-1": [[96, 411]]}, {}, {"italic": [[496, 565]]}, {}, {"quote-1": [[72, 101], [102, 122], [123, 156], [157, 168], [169, 185]]}, {}, {"judgm-2": [[80, 424], [425, 657], [658, 724], [999, 1807], [1808, 1933]], "quote-2": [[725, 793], [794, 873], [874, 947], [948, 998]]}, {}, {"italic": [[350, 352]]}, {}, {}, {}, {}, {}, {"italic": [[42, 48], [73, 81], [221, 229]]}, {}, {}, {}, {}, {"italic": [[188, 190], [413, 423], [639, 714], [736, 754]]}, {"judgm-2": [[790, 1164], [1165, 1329], [1330, 1563]], "italic": [[1398, 1406]]}, {}, {}, {}, {"judgm-2": [[270, 643], [644, 909], [910, 1014], [1015, 1080], [1081, 1204], [1205, 1381]]}, {}, {"italic": [[821, 830]]}, {"quote-1": [[160, 268]], "quote-2": [[269, 680]]}, {"italic": [[389, 399]]}, {}, {}, {}, {}, {}, {"judgm-2": [[339, 760], [761, 1257]]}, {"italic": [[223, 226]]}, {"italic": [[462, 520], [552, 599], [622, 640]]}, {}, {"italic": [[281, 288]], "quote-1": [[835, 1447]]}, {"italic": [[573, 582], [688, 713]]}, {"italic": [[285, 287], [461, 464], [551, 577], [666, 724], [764, 774], [828, 844], [861, 876], [907, 980], [1198, 1213], [1830, 2003], [2005, 2198]], "quote-1": [[826, 1121], [1122, 1303], [1304, 1827], [1828, 1829], [1830, 2199], [2200, 2216]]}, {}, {"italic": [[430, 440]], "judgm-2": [[442, 623], [624, 751], [752, 896]]}, {"judgm-2": [[105, 227], [228, 293], [294, 367]]}, {"italic": [[409, 411]]}, {"italic": [[274, 284], [1895, 1897], [1914, 1916], [2023, 2026]], "judgm-2": [[286, 433], [434, 550], [551, 801], [802, 1112], [1113, 1363], [1364, 1452], [1453, 1562], [1563, 2039]]}, {}, {"judgm-2": [[345, 560], [561, 955], [956, 1364], [1365, 1909], [1910, 2681]], "italic": [[694, 697], [738, 741], [847, 850]]}, {}, {}, {"italic": [[430, 432], [1685, 1693]]}, {}, {"italic": [[537, 539]]}, {"judgm-2": [[172, 647], [648, 1001], [1002, 1143], [1144, 1763]], "italic": [[1600, 1604]]}, {"italic": [[329, 339]]}, {}, {"italic": [[540, 542], [855, 857]]}, {}, {}, {}, {"italic": [[1034, 1039]]}, {"italic": [[776, 777]]}, {"italic": [[177, 178], [530, 590], [749, 786], [807, 821], [855, 869], [1081, 1135]], "judgm-2": [[1527, 2322], [2323, 2886], [2887, 3100]]}, {}, {"italic": [[434, 437], [593, 603]]}, {}, {"judgm-2": [[142, 181], [367, 403]], "judgm-3": [[182, 207], [208, 310], [311, 366], [404, 431], [432, 462]]}, {}, {"italic": [[496, 535], [563, 572]]}, {"italic": [[54, 105], [174, 192]], "quote-1": [[202, 646]]}, {"quote-1": [[175, 471], [472, 510]]}, {"italic": [[224, 239]]}, {"italic": [[40, 148], [174, 190]]}, {}, {"italic": [[438, 464], [492, 502]]}, {"italic": [[68, 79], [173, 175], [316, 318]]}, {"italic": [[114, 124]]}, {"quote-1": [[80, 116], [117, 218], [219, 333], [334, 572], [573, 720], [721, 725], [726, 833]]}, {"italic": [[21, 31], [256, 271], [337, 353]]}, {"italic": [[3, 19]], "quote-1": [[74, 396]]}, {"italic": [[306, 316]]}, {"italic": [[3, 13]], "quote-1": [[799, 1076]]}, {"quote-1": [[423, 812]]}, {"italic": [[313, 315], [821, 823], [1309, 1319]]}, {"italic": [[237, 298], [315, 331]], "quote-1": [[347, 515]]}, {"italic": [[53, 107], [126, 137], [211, 318], [900, 966]], "quote-1": [[155, 554], [555, 556], [557, 1162], [1163, 1179]]}, {"italic": [[318, 331], [641, 703]]}, {}, {}, {}, {"italic": [[49, 145], [168, 179]]}, {}, {"quote-1": [[211, 369]]}, {"italic": [[32, 43], [151, 170]], "quote-1": [[55, 240]], "quote-2": [[241, 782]]}, {"italic": [[201, 253], [336, 397], [425, 438], [549, 582]]}, {"italic": [[25, 92], [120, 129]], "quote-1": [[172, 539]]}, {"italic": [[94, 138], [180, 189], [360, 494]], "quote-1": [[240, 512]]}, {"quote-1": [[152, 490]]}, {}, {"italic": [[528, 530]], "quote-1": [[281, 540]]}, {"quote-1": [[115, 718]]}, {"italic": [[252, 258], [345, 351]]}, {"italic": [[66, 75]], "quote-1": [[154, 258], [259, 512]]}, {"quote-1": [[51, 624], [625, 1161]], "bold": [[911, 1135]], "italic": [[1104, 1108]]}, {"italic": [[10, 29]]}, {"quote-1": [[24, 349], [350, 692], [693, 1067], [1068, 1084]], "italic": [[444, 447], [607, 691], [693, 1067]]}, {"italic": [[48, 130], [157, 171]], "quote-1": [[303, 587]]}, {"italic": [[53, 72], [77, 91]]}, {"italic": [[145, 157]]}, {}, {"bold": [[230, 263], [1253, 1274]], "quote-1": [[230, 263], [264, 341], [386, 571], [572, 901], [1251, 1252], [1253, 1274], [1275, 1276], [1277, 1400], [1601, 1776]], "quote-2": [[342, 383], [384, 385], [902, 1094], [1095, 1250], [1401, 1402], [1403, 1598], [1599, 1600]]}, {"quote-1": [[286, 292], [293, 358], [359, 487], [488, 575], [576, 668], [669, 772], [773, 774], [775, 799]], "bold": [[362, 486]], "italic": [[387, 416]]}, {"italic": [[88, 90]]}, {}, {}, {}, {"judgm-2": [[178, 366], [367, 724], [725, 1120], [1121, 1322], [1323, 1525]], "italic": [[872, 882]]}, {"italic": [[150, 153]]}, {}, {"italic": [[265, 275]]}, {"italic": [[295, 298], [401, 412]]}, {"italic": [[90, 95]]}, {"italic": [[3, 17]]}, {"italic": [[1232, 1288]], "quote-1": [[776, 1347]]}, {"italic": [[3, 52], [75, 91]]}, {"italic": [[292, 293], [346, 361], [595, 611], [767, 800], [888, 904]]}, {}, {"italic": [[247, 263]]}, {}, {"italic": [[263, 309], [346, 372], [413, 439], [811, 837], [852, 866]]}, {"italic": [[17, 31], [263, 277]]}, {"italic": [[311, 313]]}, {}, {"italic": [[234, 259], [331, 349], [474, 518], [551, 592], [612, 629], [726, 754], [769, 803], [853, 873]], "quote-1": [[678, 976], [977, 1242]]}, {}, {}, {}, {}, {"italic": [[235, 253]]}, {}, {}, {}, {}, {}, {}, {"italic": [[19, 91], [114, 121], [125, 128]]}, {"italic": [[0, 7], [499, 503], [582, 644], [683, 729], [763, 817]]}, {}, {"italic": [[24, 31]]}, {}, {"italic": [[574, 594], [600, 645]]}, {}, {}, {}, {}, {"italic": [[247, 280], [303, 315]]}, {"italic": [[220, 232], [697, 709], [731, 738]]}, {"italic": [[181, 193], [256, 283], [294, 309], [319, 366], [372, 421]], "quote-1": [[205, 439]]}, {"italic": [[13, 25]]}, {}, {}, {}, {}, {}, {"judgm-2": [[94, 634], [635, 849], [850, 1249], [1250, 1442], [1443, 1710], [1711, 2707], [2708, 3002]], "italic": [[1063, 1071], [2405, 2406], [2683, 2684]]}, {"italic": [[564, 574]]}, {}, {}, {"italic": [[104, 169], [188, 196], [241, 249]]}, {"italic": [[626, 728], [748, 761]]}, {}, {"italic": [[150, 179], [354, 400]], "quote-1": [[240, 418]]}, {"italic": [[37, 54], [193, 195], [244, 254]]}, {"italic": [[3, 28], [47, 64]]}, {"italic": [[544, 880]], "quote-1": [[55, 898]]}, {"italic": [[0, 17], [47, 75], [94, 108]]}, {"italic": [[0, 14], [31, 77], [100, 107]]}, {}, {"italic": [[149, 163], [410, 413]]}, {"italic": [[179, 182], [490, 519], [539, 585], [608, 619]]}, {"italic": [[99, 116], [347, 366]]}, {"italic": [[30, 44], [115, 132]], "quote-1": [[143, 767]]}, {"italic": [[16, 30], [202, 262], [282, 295]]}, {"italic": [[13, 27], [125, 184], [203, 216], [252, 266]]}, {"italic": [[59, 66], [96, 109], [218, 220], [271, 343], [364, 379], [398, 412], [597, 625], [700, 713], [770, 784], [856, 873], [980, 993]]}, {}, {"italic": [[262, 269], [330, 341], [408, 437], [466, 468]]}, {"italic": [[17, 30], [109, 181], [200, 209]]}, {"italic": [[98, 101]], "quote-1": [[64, 568]]}, {"italic": [[269, 302], [321, 326], [333, 405]]}, {"italic": [[3, 10], [416, 425], [639, 653]]}, {"italic": [[11, 18], [114, 122]]}, {"italic": [[385, 396], [1302, 1318]], "quote-1": [[1144, 1548]]}, {"italic": [[262, 264]]}, {"italic": [[39, 47], [81, 89], [364, 366], [368, 373], [406, 408], [410, 417], [586, 600], [650, 658], [698, 785], [827, 889]]}, {"italic": [[92, 100], [190, 205], [207, 209], [211, 222]]}, {"italic": [[3, 18], [720, 728], [812, 826]]}, {"italic": [[3, 5], [16, 24], [610, 624]]}, {"italic": [[0, 11]]}, {"italic": [[391, 398], [526, 533]]}, {"italic": [[48, 62], [148, 159]]}, {"italic": [[91, 99], [133, 157], [175, 180], [222, 229], [234, 245], [307, 312]]}, {"italic": [[12, 25], [757, 788]]}, {"italic": [[152, 160], [362, 374], [760, 774]]}, {"italic": [[118, 132], [281, 295], [384, 397], [481, 495], [834, 848]]}, {"italic": [[144, 147]]}, {"italic": [[239, 242], [342, 345]]}, {"italic": [[111, 113], [223, 225], [384, 387]]}, {"italic": [[32, 35]]}, {"italic": [[276, 328], [348, 361]]}, {"italic": [[352, 360], [488, 496], [780, 789]]}, {"italic": [[35, 44], [454, 692], [745, 898]], "quote-1": [[175, 692], [693, 898], [899, 915]]}, {"italic": [[63, 77], [182, 196]]}, {"italic": [[72, 85], [188, 202], [347, 360], [583, 596], [622, 636], [696, 711], [845, 858]]}, {"italic": [[165, 179], [314, 328], [421, 435], [702, 716]]}, {}, {}, {"quote-1": [[145, 331]]}, {"italic": [[14, 89], [367, 450], [473, 478]]}, {}, {"italic": [[736, 825]]}, {}, {}, {"italic": [[484, 587], [614, 629]]}, {"italic": [[186, 191], [602, 614], [629, 644]]}, {"italic": [[32, 47], [341, 354], [502, 517]]}, {}, {"quote-1": [[858, 1137]]}, {"italic": [[575, 610], [632, 645]]}, {"italic": [[43, 58]]}, {"italic": [[517, 527]]}, {"italic": [[281, 283]]}, {"italic": [[59, 74]]}, {"italic": [[25, 40]]}, {"italic": [[138, 176], [193, 204], [324, 421], [465, 494], [697, 698], [967, 978]]}, {}, {"italic": [[393, 406]]}, {}, {}, {}, {"italic": [[171, 190], [390, 392]]}, {}], "tags": ["Admiralty and Shipping"]}