{"author": "Lee Seiu Kin J:", "casenumber": "Originating Summons No 946 of 2011", "casename": "Alain Moni\u00e9 v APRIL Management Pte Ltd", "citation": "[2012] SGHC 160", "coram": "Lee Seiu Kin J", "counsel": "Tan Chuan Thye, Germaine Chia and Loh Jien Li (Stamford Law Corporation) for the plaintiff; Chew Kei-Jin and Teo Jun Wei Andre (Tan Rajah & Cheah) for the defendant.", "decorations": [{}, {}, {}, {}, {}, {}, {}, {}, {"judgm-2": [[166, 206], [207, 250], [251, 293], [294, 339], [340, 390], [391, 436]]}, {"italic": [[80, 90]]}, {}, {}, {}, {"judgm-2": [[572, 700], [701, 719], [720, 784]]}, {"italic": [[199, 209]]}, {"italic": [[188, 297], [580, 787]], "quote-1": [[35, 368], [369, 477], [478, 573], [574, 865], [866, 1057], [1058, 1259], [1260, 1276]]}, {"italic": [[107, 110], [308, 311]], "judgm-2": [[73, 247], [248, 459]]}, {"italic": [[398, 525], [1168, 1217]], "quote-1": [[189, 848], [849, 1368], [1369, 1385]]}, {}, {}, {"quote-1": [[202, 527]], "italic": [[536, 543], [743, 750]], "quote-2": [[528, 636], [637, 732], [733, 1024], [1025, 1216], [1217, 1418], [1419, 1435]]}, {"italic": [[1043, 1046], [1237, 1241]]}, {}, {}, {"italic": [[204, 207], [402, 410], [641, 696], [733, 736], [921, 924]]}, {"italic": [[750, 765]]}, {}, {}, {"judgm-2": [[142, 255], [256, 319], [320, 394]]}, {}, {}], "tags": ["Contract/Contractual terms"]}