{"author": "Aedit Abdullah:", "casenumber": "Divorce Transfer No 6172 of 2011", "casename": "ARV v ARW", "citation": "[2015] SGHC 72", "coram": "Aedit Abdullah", "counsel": "Loh Wai Mooi, Ho Shiao Hong (Bih Li & Lee) for the plaintiff; The defendant in person.", "decorations": [{}, {}, {}, {}, {}, {}, {}, {}, {}, {}, {}, {}, {}, {"italic": [[205, 214], [232, 237], [244, 251], [274, 281], [292, 295], [393, 396]], "quote-1": [[408, 837], [838, 1327]]}, {"italic": [[92, 99], [354, 361]]}, {}, {}, {}, {}, {}, {"judgm-2": [[421, 674], [675, 909], [910, 1124], [1125, 1404]]}, {}, {"judgm-2": [[139, 169], [170, 432], [433, 653], [654, 665], [666, 712], [713, 751], [752, 773], [774, 786], [787, 803], [804, 862], [863, 881], [882, 1114]]}, {}, {}, {"italic": [[135, 144]]}, {}, {}, {}, {}, {}, {}, {}, {}, {}, {"italic": [[377, 388]]}, {}, {}, {}, {}, {}, {}, {"judgm-2": [[63, 151], [152, 222], [223, 272], [273, 312], [313, 355], [356, 422], [423, 560], [561, 633], [634, 769], [770, 824], [825, 1004], [1005, 1097], [1098, 1151], [1152, 1211], [1212, 1325], [1326, 1830]]}, {"italic": [[327, 330]]}, {}, {}, {}, {}, {}, {}, {"italic": [[212, 221]]}, {}, {}, {}, {}, {}, {}, {}, {"italic": [[190, 219], [380, 391]], "judgm-2": [[332, 425], [426, 522]]}, {"judgm-2": [[92, 138], [139, 266], [267, 326]]}, {"italic": [[257, 310], [490, 497]]}, {}, {}, {"judgm-2": [[103, 167], [168, 294], [295, 344], [345, 414], [415, 465]]}, {}, {}, {}, {}, {}, {"italic": [[173, 240]]}, {}, {}, {}, {}, {}, {"italic": [[213, 223], [592, 614]]}, {"italic": [[203, 204], [602, 603]]}, {}, {}], "tags": ["Family Law/Maintenance", "Family Law/Matrimonial Assets/Division"]}