{"author": "Andrew Phang Boon Leong JA (delivering the judgment of the court):", "casenumber": "Civil Appeals Nos 77 and 79 of 2014", "casename": "Ng Chee Weng v Lim Jit Ming Bryan and another and another appeal", "citation": "[2015] SGCA 13", "coram": "Sundaresh Menon CJ; Andrew Phang Boon Leong JA; Steven Chong J", "counsel": "Richard Lester Millett QC, Narayanan Vijya Kumar and Niroze Idroos (Vijay & Co) for the appellant in Civil Appeal No 77 of 2014 and the respondent in Civil Appeal No 79 of 2014; Cavinder Bull SC, Woo Shu Yan, Lin Shumin, Vikram Raja Rajaram and Tan Yuan Kheng (Drew & Napier LLC) for the respondents in Civil Appeal No 77 of 2014 and the appellants in Civil Appeal No 79 of 2014.", "decorations": [{"italic": [[411, 418]]}, {"italic": [[1220, 1226]]}, {"italic": [[130, 175], [595, 599]]}, {"italic": [[418, 420]]}, {}, {"italic": [[389, 393]]}, {}, {}, {}, {"italic": [[131, 133]]}, {}, {}, {}, {}, {}, {}, {}, {}, {}, {"italic": [[0, 7]]}, {}, {"italic": [[246, 249]], "quote-1": [[117, 419]]}, {"italic": [[773, 785]]}, {}, {}, {}, {}, {"italic": [[0, 7], [13, 30]]}, {}, {}, {"italic": [[1050, 1066]]}, {"italic": [[66, 76], [1041, 1044]], "judgm-2": [[151, 559], [560, 788], [789, 1185], [1186, 1508]]}, {}, {"italic": [[83, 86]]}, {"italic": [[428, 432], [510, 521]]}, {"italic": [[68, 76]]}, {"italic": [[17, 28]]}, {"italic": [[116, 121], [602, 610], [1121, 1125], [1637, 1639], [2043, 2053], [2172, 2182]], "judgm-2": [[479, 740], [741, 1022], [1023, 1334], [1335, 1819], [1820, 2427], [2428, 2612], [2613, 3026]]}, {}, {"italic": [[252, 255]]}, {"italic": [[31, 48], [330, 332], [452, 454]]}, {"judgm-2": [[147, 606], [607, 1099], [1100, 1612]]}, {"italic": [[38, 49], [121, 131]], "judgm-2": [[187, 536], [537, 876], [877, 1619]]}, {}, {}, {}, {"italic": [[189, 193], [757, 774], [867, 870]]}, {}, {"italic": [[4, 19]]}, {}, {"italic": [[255, 268], [465, 473]]}, {"italic": [[371, 382]]}, {}, {}, {}, {}, {"italic": [[91, 108]], "underline": [[939, 942]], "quote-1": [[815, 1070], [1071, 1616], [1617, 1642]]}, {}, {}, {}, {}, {"italic": [[447, 450], [727, 732]]}, {}, {}, {}, {"italic": [[27, 81], [158, 218], [561, 747]], "quote-1": [[307, 1053]]}, {"italic": [[537, 543]]}, {"italic": [[315, 374], [792, 799], [816, 825]], "judgm-2": [[855, 1112], [1113, 1361], [1362, 1568]]}, {"italic": [[64, 69]]}, {}, {}, {}, {"quote-1": [[65, 362], [363, 873], [874, 1058]]}, {"italic": [[148, 151]]}, {"italic": [[113, 123], [202, 212], [313, 317]]}, {"italic": [[344, 347]]}, {}, {"italic": [[316, 320], [412, 416], [686, 698], [814, 818], [878, 882]]}, {}, {}, {"italic": [[146, 162], [596, 599], [917, 930]]}, {"italic": [[459, 479], [493, 495], [1811, 1818], [1895, 1906], [2059, 2061], [2241, 2257], [2283, 2292]]}, {"italic": [[158, 161], [283, 295], [855, 857], [929, 933], [1211, 1214], [1322, 1338], [1366, 1369], [1451, 1468]]}, {"italic": [[550, 554]]}, {}, {}, {}, {}, {"italic": [[143, 146]]}, {"italic": [[322, 350]]}, {"italic": [[703, 707], [1048, 1058], [1151, 1160], [1241, 1244], [1385, 1432], [1480, 1487]]}, {}, {"italic": [[502, 509]]}, {"italic": [[1212, 1234], [1866, 1869], [2275, 2284]]}, {"italic": [[1035, 1038], [1129, 1133], [1166, 1176], [1319, 1323]]}, {"italic": [[97, 104]]}, {}, {"italic": [[355, 358], [419, 431]]}, {"italic": [[98, 101], [178, 187]]}, {}, {}, {}, {}, {"italic": [[149, 151]]}], "tags": ["Trusts/True beneficial ownership", "Contract/Formation/Whether there was a binding settlement agreement", "Contract/Repudiation/Whether plaintiff repudiated the settlement agreement"], "other_judges": ["Sundaresh Menon CJ", "Steven Chong J"]}