{"author": "Tay Yong Kwang JA (delivering the grounds of decision of the court):", "casenumber": "Court of Appeal \u2014 Criminal Appeal No 21 of 2016", "casename": "Suventher Shanmugam v Public Prosecutor", "citation": "[2017] SGCA 25", "coram": "Sundaresh Menon CJ, Judith Prakash JA and Tay Yong Kwang JA", "counsel": "Appellant in person;Wong Woon Kwong and Chan Yi Cheng (Attorney-General\u2019s Chambers) for the respondent.", "decorations": [{}, {"italic": [[339, 378]]}, {}, {}, {}, {}, {}, {}, {}, {}, {"italic": [[496, 548], [566, 572], [576, 627], [646, 658], [666, 706], [726, 732]]}, {}, {}, {}, {}, {}, {"italic": [[162, 202], [221, 229]]}, {}, {}, {}, {"italic": [[407, 459], [695, 703]]}, {}, {"italic": [[694, 747], [775, 788], [1035, 1084], [1388, 1423], [1451, 1466], [1877, 1935], [1953, 1966], [2389, 2396], [2815, 2865], [3123, 3171], [3188, 3199], [3473, 3514], [3531, 3541], [3854, 3901]]}, {"italic": [[45, 47], [60, 73], [75, 76]]}, {"italic": [[175, 190], [392, 405]]}, {}, {"italic": [[144, 183], [521, 562], [593, 604]], "blockquote": [[771, 1040]]}, {"italic": [[227, 235], [418, 426], [616, 639], [714, 762], [830, 878], [897, 909]]}, {"italic": [[24, 32], [118, 126], [235, 243], [312, 320], [409, 417]]}, {"italic": [[376, 385]]}, {"italic": [[45, 53]]}, {}, {}, {"italic": [[191, 198], [209, 216], [228, 241], [288, 299], [311, 324], [380, 391], [393, 399], [401, 411], [416, 428]]}, {}, {"italic": [[202, 234], [899, 905]], "blockquote": [[274, 751]]}, {}, {}, {}, {"italic": [[376, 391], [417, 418], [813, 828]]}, {}, {}, {}], "dates": "18 January 2017", "tags": ["Criminal Procedure and Sentencing/Sentencing/Benchmark sentences"], "other_judges": ["Sundaresh Menon CJ", "Judith Prakash JA"]}