{"author": "Audrey Lim JC:", "casenumber": "High Court \u2014 Criminal Case No 51 of 2018", "casename": "Public Prosecutor v Lingkesvaran Rajendaren and another", "citation": "[2018] SGHC 234", "coram": "Audrey Lim JC", "counsel": "Anandan Bala, Tan Yanying and Theong Li Han (Attorney-General\u2019s Chambers) for the Prosecution;Ram Goswami (Ram Goswami) and Cheng Kim Kuan (K K Cheng & Co) for the first accused;Luo Ling Ling (RHT Law Tay Wessing LLP), Prasad s/o Karunakarn (K Prasad & Co) and Krishna Ramakrishna Sharma (Krishna R Sharma) for the second accused.", "decorations": [{}, {"blockquote": [[203, 240], [241, 909], [910, 910], [911, 947], [948, 1635]], "italic": [[431, 437], [1156, 1162]]}, {}, {"italic": [[125, 126], [451, 452]]}, {}, {}, {}, {}, {}, {}, {}, {}, {}, {}, {"italic": [[671, 674]]}, {}, {}, {}, {}, {}, {}, {}, {}, {}, {"italic": [[323, 325]]}, {}, {}, {}, {}, {}, {}, {}, {}, {}, {"italic": [[428, 430]]}, {}, {"italic": [[14, 15], [261, 262]], "bold": [[46, 77], [78, 80]], "blockquote": [[46, 77], [78, 259], [260, 296], [297, 299], [300, 468]]}, {"italic": [[18, 50], [83, 132], [232, 233], [245, 246], [276, 277], [599, 600], [740, 741]]}, {"bold": [[102, 161], [162, 165]], "blockquote": [[102, 161], [162, 260], [261, 304], [305, 307], [308, 398], [399, 575]], "italic": [[263, 264]]}, {"italic": [[61, 77], [78, 116], [134, 140], [661, 662]]}, {"italic": [[287, 293], [375, 377]]}, {"italic": [[487, 539], [558, 571], [587, 621], [1444, 1512], [1518, 1739]], "blockquote": [[682, 1333], [1334, 1335], [1336, 1514], [1515, 1988], [1989, 2005]]}, {}, {}, {}, {}, {}, {"italic": [[77, 81], [90, 97], [221, 229], [756, 761], [786, 793], [958, 965], [1367, 1372]]}, {}, {}, {}, {}, {}, {}, {}, {}, {}, {"italic": [[1088, 1100]]}, {"italic": [[548, 557], [1579, 1581]]}, {}, {}, {"italic": [[224, 237], [472, 475], [873, 880], [896, 901], [903, 904], [919, 926], [927, 931]]}, {}, {}, {}, {}, {}, {"italic": [[491, 493]]}, {}, {}, {}, {"italic": [[1022, 1029], [1264, 1269]]}, {"italic": [[664, 678]]}, {}, {}, {"italic": [[420, 421]]}, {"italic": [[153, 154], [168, 170], [807, 808]]}, {"italic": [[107, 108]]}, {}], "dates": "25\u201326, 31 July; 1\u20133, 7 August; 15 October 2018", "tags": ["Criminal procedure and sentencing/Sentencing", "Criminal Law/Statutory offences/Misuse of Drugs Act"]}