{"author": "Vivian Ramsey IJ:", "casenumber": "Singapore International Commercial Court \u2014 Suit No 5 of 2016", "casename": "CPIT Investments Limited v Qilin World Capital Limited and another", "citation": "[2018] SGHC(I) 02", "coram": "Vivian Ramsey IJ", "counsel": "Tan Poh Ling Wendy and Chua Han Yuan, Kenneth (Morgan Lewis Stamford LLC) for the plaintiff;Sharon Chong Chin Yee and Gideon Yap (RHTLaw Taylor Wessing LLP) for the defendants.", "decorations": [{}, {"italic": [[292, 351]]}, {}, {}, {}, {}, {"italic": [[544, 604], [623, 628]]}, {}, {"italic": [[39, 69]]}, {"italic": [[148, 153], [212, 213]]}, {}, {"bold": [[95, 116], [117, 120]], "blockquote": [[95, 116], [117, 318], [319, 573], [574, 652], [653, 801], [802, 910], [911, 995], [996, 1027], [1028, 1114], [1115, 1209], [1210, 1401], [1402, 1442], [1443, 1472], [1473, 1526], [1527, 1638]], "italic": [[654, 655], [803, 804], [912, 913], [997, 998], [1029, 1030], [1444, 1445], [1474, 1475], [1528, 1529]]}, {}, {}, {}, {"bold": [[225, 232]], "blockquote": [[225, 232], [233, 445], [446, 481], [482, 746], [747, 756], [757, 991], [992, 1050], [1051, 1098], [1099, 1164], [1165, 1226], [1227, 1268], [1269, 1336], [1337, 1631], [1632, 1748]]}, {"italic": [[793, 794]]}, {}, {"bold": [[229, 250]], "blockquote": [[229, 250], [251, 560], [561, 888], [889, 1030]]}, {"bold": [[40, 70]], "blockquote": [[40, 70], [71, 180], [181, 522], [523, 926], [927, 1087], [1088, 1279], [1280, 1353]]}, {}, {"italic": [[64, 69], [147, 152], [441, 447]]}, {}, {"italic": [[190, 191], [203, 204], [275, 276], [366, 367]], "blockquote": [[238, 271], [272, 273], [274, 364], [365, 566]]}, {}, {"italic": [[323, 324]]}, {}, {}, {"italic": [[124, 127], [250, 251], [377, 378], [762, 763], [909, 910], [1281, 1282], [1408, 1409], [1748, 1749], [1975, 1976]], "bold": [[174, 194], [195, 197], [2549, 2584], [2585, 2588]], "blockquote": [[174, 194], [195, 248], [249, 375], [376, 510], [511, 693], [694, 760], [761, 907], [908, 1228], [1229, 1279], [1280, 1406], [1407, 1539], [1540, 1742], [1743, 1973], [1974, 2203], [2204, 2546], [2547, 2548], [2549, 2584], [2585, 2890]]}, {"italic": [[534, 629]]}, {"italic": [[228, 231]]}, {}, {}, {"italic": [[451, 460]]}, {}, {}, {}, {}, {}, {}, {}, {"italic": [[1711, 1720]]}, {}, {}, {}, {}, {}, {}, {}, {}, {}, {}, {}], "dates": "28 September 2017", "tags": ["Civil Procedure/Offer to settle/Singapore International Commercial Court", "Civil Procedure/Costs/Principles/Singapore International Commercial Court"]}