{"author": "Lee Seiu Kin J:", "casenumber": "High Court \u2014 Originating Summons (Bankruptcy) No 4 of 2018 (Registrar\u2019s Appeal No 18 of 2018, Summons No 889, 954 and 2149 of 2018, Bankruptcy No 824 of 2017 (Registrar\u2019s Appeal No 19 of 2018, Summons No 840 and 2150 of 2018)", "casename": "Re Andrla, Dominic and another matter", "citation": "[2019] SGHC 77", "coram": "Lee Seiu Kin J", "counsel": "Melissa Peh (Yeo-Leong & Peh LLC) for the plaintiff; Nandwani Manoj Prakash (Gabriel Law Corporation) for the defendant.", "decorations": [{}, {}, {}, {}, {}, {}, {}, {}, {"italic": [[239, 240]]}, {"italic": [[470, 471]]}, {}, {}, {}, {}, {"italic": [[443, 444], [446, 447], [461, 462], [464, 466]]}, {}, {"italic": [[3, 25], [62, 103], [352, 370], [523, 541], [909, 923], [971, 983], [984, 1001]], "blockquote": [[191, 1044], [1045, 1061]]}, {}, {}, {}, {}, {}, {}, {}, {"italic": [[73, 94]]}, {}, {}, {}, {"italic": [[126, 127]]}, {"italic": [[50, 51], [79, 80], [272, 314], [497, 532]]}, {}, {}], "dates": "17, 31 May; 25 June 2018", "tags": ["Insolvency/Bankruptcy/Interim Order"], "tags-parsed": ["Insolvency Law/Bankruptcy/Interim Order"]}