{"author": "Tay Yong Kwang JA (delivering the grounds of decision of the court):", "casenumber": "Court of Appeal \u2014 Criminal Motion No 6 of 2020", "casename": "Yuen Ye Ming v Public Prosecutor", "citation": "[2020] SGCA 80", "coram": "Sundaresh Menon CJ, Judith Prakash JA, Tay Yong Kwang JA", "counsel": ["Ravi s/o Madasamy (Carson Law Chambers) for the applicant; andNg Yiwen, Benedict Chan and Rimplejit Kaur (Attorney General\u2019s Chambers) for the respondent."], "decorations": [{}, {"italic": [[114, 146], [166, 178]]}, {}, {}, {}, {}, {"italic": [[306, 367]]}, {"italic": [[728, 809]]}, {"italic": [[127, 159], [527, 539]]}, {}, {}, {}, {}, {}, {"blockquote": [[58, 237], [1067, 1146], [1147, 1297], [1298, 1751]], "italic": [[599, 605], [606, 646], [775, 778], [1434, 1440]], "bold": [[599, 605], [606, 644]]}, {}, {"italic": [[98, 142], [162, 175]]}, {"italic": [[115, 192], [211, 229], [288, 316], [428, 684]], "blockquote": [[428, 686], [687, 709]]}, {"italic": [[317, 332], [333, 335], [455, 456], [505, 506]], "bold": [[376, 378]], "blockquote": [[376, 453], [454, 503], [504, 559], [560, 615], [616, 638]]}, {}, {"italic": [[76, 89]]}, {"italic": [[65, 84], [342, 378], [445, 485], [507, 517]], "blockquote": [[923, 1303]]}, {}, {"italic": [[46, 56]]}, {"italic": [[4, 62]], "blockquote": [[653, 1151]]}, {"italic": [[123, 133]]}, {"italic": [[402, 437]]}, {}, {"italic": [[195, 237], [520, 575]]}, {"italic": [[417, 430]]}, {}, {"italic": [[757, 801]]}, {"italic": [[404, 438]]}, {"bold": [[243, 253]]}, {}], "dates": "12 August 2020", "tags": ["Criminal Law/Statutory offences/Misuse of Drugs Act", "Criminal Procedure and Sentencing/Criminal references/Extension of time", "Criminal Procedure and Sentencing/Criminal references/Leave to refer questions of law of public interest"], "other_judges": ["Sundaresh Menon CJ", "Judith Prakash JA"]}