{"author": "Debbie Ong J:", "casenumber": "High Court (Family Division) \u2014 District Court Appeal Nos 115 and 116 of 2019", "casename": "VDX v VDY and another appeal", "citation": "[2021] SGHCF 2", "coram": "Debbie Ong J", "counsel": "Siraj Omar SC, Khoo Boo Teck Randolph, Hoon Shu Mei Sumathi and Goh Ting Xuan Beverly (Drew & Napier LLC) for the appellant in HCF/DCA 115/2019 and the respondent in HCF/DCA 116/2019;Lee Eng Beng SC, Kee Lay Lian and Ada Chua Ai Le (Rajah & Tann Singapore LLP) for the respondent in HCF/DCA 115/2019 and the appellant in HCF/DCA 116/2019.", "headings": [{"type": "h1", "text": "Introduction", "para": 2}, {"type": "h1", "text": "Background", "para": 3}, {"type": "h1", "text": "The proceedings below", "para": 8}, {"type": "h1", "text": "The appeals", "para": 17}, {"type": "h1", "text": "My decision", "para": 24}, {"type": "h2", "text": "Dinner on Chinese New Year\u2019s Eve", "para": 30}, {"type": "h2", "text": "Handover after December holidays", "para": 33}, {"type": "h1", "text": "Conclusion", "para": 38}], "decorations": [{}, {}, {}, {}, {}, {}, {}, {"italic": [[112, 122]]}, {"italic": [[121, 131]]}, {}, {}, {}, {}, {"italic": [[32, 42]]}, {}, {}, {}, {}, {}, {}, {}, {}, {}, {"italic": [[451, 461], [494, 530], [552, 559], [574, 582], [748, 756]]}, {}, {"italic": [[491, 495], [534, 538], [669, 675]]}, {}, {"italic": [[605, 634], [1380, 1506]], "blockquote": [[657, 1506], [1507, 1523]]}, {"italic": [[200, 205], [220, 226], [227, 238], [246, 264], [273, 279], [565, 598], [629, 648]]}, {}, {"italic": [[823, 876], [1075, 1078], [1163, 1169], [1248, 1308], [1332, 1355]]}, {"italic": [[896, 919]]}, {}, {}, {}, {}, {}, {}, {"italic": [[671, 680], [1223, 1231]], "blockquote": [[707, 1248]]}, {}, {}, {}], "dates": "1 October 2020; 26 October 2020", "tags": ["Family Law/Variation/Care and control"]}